neuralforge/__init__.py
neuralforge/cli.py
neuralforge/config.py
neuralforge/decorators.py
neuralforge/log_config.py
neuralforge/testing.py
neuralforge/validators.py
neuralforge/auth/__init__.py
neuralforge/auth/manager.py
neuralforge/benchmarks/__init__.py
neuralforge/benchmarks/comparison.py
neuralforge/benchmarks/memory.py
neuralforge/benchmarks/reporters.py
neuralforge/benchmarks/runner.py
neuralforge/benchmarks/streaming.py
neuralforge/cache/__init__.py
neuralforge/cache/manager.py
neuralforge/db/__init__.py
neuralforge/db/base.py
neuralforge/db/manager.py
neuralforge/db/models/__init__.py
neuralforge/db/models/ab_assignment.py
neuralforge/db/models/ab_experiment.py
neuralforge/db/models/ab_metric.py
neuralforge/db/models/ab_variant.py
neuralforge/db/models/alert_rule.py
neuralforge/db/models/api_key.py
neuralforge/db/models/benchmark_result.py
neuralforge/db/models/drift_baseline.py
neuralforge/db/models/drift_detection.py
neuralforge/db/models/ml_model.py
neuralforge/db/models/optimized_model.py
neuralforge/db/models/prediction.py
neuralforge/db/models/prediction_alert.py
neuralforge/db/models/prediction_metric.py
neuralforge/dependencies/__init__.py
neuralforge/dependencies/common.py
neuralforge/dependencies/core.py
neuralforge/dependencies/resolver.py
neuralforge/grpc/__init__.py
neuralforge/grpc/interceptors.py
neuralforge/grpc/server.py
neuralforge/grpc/proto/inference.proto
neuralforge/health/__init__.py
neuralforge/health/checker.py
neuralforge/http/__init__.py
neuralforge/http/request.py
neuralforge/kubernetes/__init__.py
neuralforge/kubernetes/manifests.py
neuralforge/kubernetes/operator.py
neuralforge/kubernetes/scaling.py
neuralforge/metrics/__init__.py
neuralforge/metrics/collector.py
neuralforge/middleware/__init__.py
neuralforge/middleware/base.py
neuralforge/middleware/chain.py
neuralforge/middleware/cors.py
neuralforge/middleware/error_handler.py
neuralforge/middleware/logging.py
neuralforge/middleware/rate_limit.py
nforge-1.1.2.dist-info/licenses/LICENSE
nforge-1.1.2.dist-info/METADATA
nforge-1.1.2.dist-info/WHEEL
nforge-1.1.2.dist-info/entry_points.txt
nforge-1.1.2.dist-info/top_level.txt
nforge-1.1.2.dist-info/RECORD
