Metadata-Version: 2.4
Name: nforge
Version: 1.1.2
Summary: The ML API Framework - FastAPI for Machine Learning
Home-page: https://github.com/rockstream/neuralforge
Author: NeuralForge Team
Author-email: NeuralForge Team <team@neuralforge.dev>
Maintainer-email: NeuralForge Team <team@neuralforge.dev>
License: MIT
Project-URL: Homepage, https://github.com/rockstream/neuralforge
Project-URL: Documentation, https://github.com/rockstream/neuralforge#readme
Project-URL: Repository, https://github.com/rockstream/neuralforge.git
Project-URL: Issues, https://github.com/rockstream/neuralforge/issues
Project-URL: Changelog, https://github.com/rockstream/neuralforge/blob/main/CHANGELOG.md
Keywords: machine-learning,ml-serving,api-framework,model-serving,llm,inference,pytorch,tensorflow,mlops,grpc,streaming
Classifier: Development Status :: 4 - Beta
Classifier: Intended Audience :: Developers
Classifier: Intended Audience :: Science/Research
Classifier: Topic :: Software Development :: Libraries :: Application Frameworks
Classifier: Topic :: Scientific/Engineering :: Artificial Intelligence
Classifier: License :: OSI Approved :: MIT License
Classifier: Programming Language :: Python :: 3
Classifier: Programming Language :: Python :: 3.10
Classifier: Programming Language :: Python :: 3.11
Classifier: Programming Language :: Python :: 3.12
Classifier: Operating System :: OS Independent
Classifier: Framework :: AsyncIO
Classifier: Typing :: Typed
Requires-Python: >=3.10
License-File: LICENSE
Requires-Dist: pydantic>=2.0.0
Requires-Dist: pydantic-settings>=2.0.0
Requires-Dist: uvicorn[standard]>=0.23.0
Requires-Dist: python-multipart>=0.0.6
Requires-Dist: python-jose[cryptography]>=3.3.0
Requires-Dist: passlib[bcrypt]>=1.7.4
Requires-Dist: httpx>=0.24.0
Requires-Dist: aiofiles>=23.0.0
Requires-Dist: asyncio>=3.4.3
Requires-Dist: sqlalchemy[asyncio]>=2.0.0
Requires-Dist: alembic>=1.11.0
Requires-Dist: asyncpg>=0.28.0
Requires-Dist: aiomysql>=0.2.0
Requires-Dist: aiosqlite>=0.19.0
Requires-Dist: redis>=4.6.0
Requires-Dist: hiredis>=2.2.0
Requires-Dist: prometheus-client>=0.17.0
Requires-Dist: opentelemetry-api>=1.19.0
Requires-Dist: opentelemetry-sdk>=1.19.0
Requires-Dist: opentelemetry-instrumentation>=0.40b0
Requires-Dist: orjson>=3.9.0
Requires-Dist: msgpack>=1.0.5
Requires-Dist: python-dotenv>=1.0.0
Requires-Dist: click>=8.1.0
Requires-Dist: rich>=13.5.0
Requires-Dist: tenacity>=8.2.0
Provides-Extra: dev
Requires-Dist: pytest>=7.0.0; extra == "dev"
Requires-Dist: pytest-asyncio>=0.21.0; extra == "dev"
Requires-Dist: pytest-cov>=4.0.0; extra == "dev"
Requires-Dist: black>=23.0.0; extra == "dev"
Requires-Dist: flake8>=6.0.0; extra == "dev"
Requires-Dist: mypy>=1.0.0; extra == "dev"
Requires-Dist: isort>=5.12.0; extra == "dev"
Provides-Extra: docs
Requires-Dist: mkdocs>=1.4.0; extra == "docs"
Requires-Dist: mkdocs-material>=9.0.0; extra == "docs"
Requires-Dist: mkdocstrings[python]>=0.20.0; extra == "docs"
Provides-Extra: pytorch
Requires-Dist: torch>=2.0.0; extra == "pytorch"
Requires-Dist: torchvision>=0.15.0; extra == "pytorch"
Provides-Extra: tensorflow
Requires-Dist: tensorflow>=2.13.0; extra == "tensorflow"
Provides-Extra: onnx
Requires-Dist: onnxruntime>=1.15.0; extra == "onnx"
Provides-Extra: grpc
Requires-Dist: grpcio>=1.50.0; extra == "grpc"
Requires-Dist: grpcio-tools>=1.50.0; extra == "grpc"
Requires-Dist: protobuf>=4.21.0; extra == "grpc"
Provides-Extra: all
Requires-Dist: torch>=2.0.0; extra == "all"
Requires-Dist: tensorflow>=2.13.0; extra == "all"
Requires-Dist: onnxruntime>=1.15.0; extra == "all"
Requires-Dist: transformers>=4.30.0; extra == "all"
Requires-Dist: sentence-transformers>=2.2.0; extra == "all"
Requires-Dist: grpcio>=1.50.0; extra == "all"
Requires-Dist: grpcio-tools>=1.50.0; extra == "all"
Dynamic: author
Dynamic: home-page
Dynamic: license-file
Dynamic: requires-python
